{ "frames": [
   {
    "filename": "frame-leo 0.aseprite",
    "frame": { "x": 0, "y": 0, "w": 96, "h": 96 },
    "rotated": false,
    "trimmed": false,
    "spriteSourceSize": { "x": 0, "y": 0, "w": 96, "h": 96 },
    "sourceSize": { "w": 96, "h": 96 },
    "duration": 71
   },
   {
    "filename": "frame-leo 1.aseprite",
    "frame": { "x": 0, "y": 0, "w": 96, "h": 96 },
    "rotated": false,
    "trimmed": false,
    "spriteSourceSize": { "x": 0, "y": 0, "w": 96, "h": 96 },
    "sourceSize": { "w": 96, "h": 96 },
    "duration": 71
   },
   {
    "filename": "frame-leo 2.aseprite",
    "frame": { "x": 96, "y": 0, "w": 96, "h": 96 },
    "rotated": false,
    "trimmed": false,
    "spriteSourceSize": { "x": 0, "y": 0, "w": 96, "h": 96 },
    "sourceSize": { "w": 96, "h": 96 },
    "duration": 71
   },
   {
    "filename": "frame-leo 3.aseprite",
    "frame": { "x": 96, "y": 0, "w": 96, "h": 96 },
    "rotated": false,
    "trimmed": false,
    "spriteSourceSize": { "x": 0, "y": 0, "w": 96, "h": 96 },
    "sourceSize": { "w": 96, "h": 96 },
    "duration": 71
   },
   {
    "filename": "frame-leo 4.aseprite",
    "frame": { "x": 96, "y": 0, "w": 96, "h": 96 },
    "rotated": false,
    "trimmed": false,
    "spriteSourceSize": { "x": 0, "y": 0, "w": 96, "h": 96 },
    "sourceSize": { "w": 96, "h": 96 },
    "duration": 71
   },
   {
    "filename": "frame-leo 5.aseprite",
    "frame": { "x": 96, "y": 0, "w": 96, "h": 96 },
    "rotated": false,
    "trimmed": false,
    "spriteSourceSize": { "x": 0, "y": 0, "w": 96, "h": 96 },
    "sourceSize": { "w": 96, "h": 96 },
    "duration": 71
   },
   {
    "filename": "frame-leo 6.aseprite",
    "frame": { "x": 192, "y": 0, "w": 96, "h": 96 },
    "rotated": false,
    "trimmed": false,
    "spriteSourceSize": { "x": 0, "y": 0, "w": 96, "h": 96 },
    "sourceSize": { "w": 96, "h": 96 },
    "duration": 71
   },
   {
    "filename": "frame-leo 7.aseprite",
    "frame": { "x": 192, "y": 0, "w": 96, "h": 96 },
    "rotated": false,
    "trimmed": false,
    "spriteSourceSize": { "x": 0, "y": 0, "w": 96, "h": 96 },
    "sourceSize": { "w": 96, "h": 96 },
    "duration": 71
   },
   {
    "filename": "frame-leo 8.aseprite",
    "frame": { "x": 288, "y": 0, "w": 96, "h": 96 },
    "rotated": false,
    "trimmed": false,
    "spriteSourceSize": { "x": 0, "y": 0, "w": 96, "h": 96 },
    "sourceSize": { "w": 96, "h": 96 },
    "duration": 71
   },
   {
    "filename": "frame-leo 9.aseprite",
    "frame": { "x": 288, "y": 0, "w": 96, "h": 96 },
    "rotated": false,
    "trimmed": false,
    "spriteSourceSize": { "x": 0, "y": 0, "w": 96, "h": 96 },
    "sourceSize": { "w": 96, "h": 96 },
    "duration": 71
   },
   {
    "filename": "frame-leo 10.aseprite",
    "frame": { "x": 384, "y": 0, "w": 96, "h": 96 },
    "rotated": false,
    "trimmed": false,
    "spriteSourceSize": { "x": 0, "y": 0, "w": 96, "h": 96 },
    "sourceSize": { "w": 96, "h": 96 },
    "duration": 71
   },
   {
    "filename": "frame-leo 11.aseprite",
    "frame": { "x": 0, "y": 96, "w": 96, "h": 96 },
    "rotated": false,
    "trimmed": false,
    "spriteSourceSize": { "x": 0, "y": 0, "w": 96, "h": 96 },
    "sourceSize": { "w": 96, "h": 96 },
    "duration": 71
   },
   {
    "filename": "frame-leo 12.aseprite",
    "frame": { "x": 96, "y": 96, "w": 96, "h": 96 },
    "rotated": false,
    "trimmed": false,
    "spriteSourceSize": { "x": 0, "y": 0, "w": 96, "h": 96 },
    "sourceSize": { "w": 96, "h": 96 },
    "duration": 71
   },
   {
    "filename": "frame-leo 13.aseprite",
    "frame": { "x": 192, "y": 96, "w": 96, "h": 96 },
    "rotated": false,
    "trimmed": false,
    "spriteSourceSize": { "x": 0, "y": 0, "w": 96, "h": 96 },
    "sourceSize": { "w": 96, "h": 96 },
    "duration": 71
   },
   {
    "filename": "frame-leo 14.aseprite",
    "frame": { "x": 288, "y": 96, "w": 96, "h": 96 },
    "rotated": false,
    "trimmed": false,
    "spriteSourceSize": { "x": 0, "y": 0, "w": 96, "h": 96 },
    "sourceSize": { "w": 96, "h": 96 },
    "duration": 71
   },
   {
    "filename": "frame-leo 15.aseprite",
    "frame": { "x": 384, "y": 96, "w": 96, "h": 96 },
    "rotated": false,
    "trimmed": false,
    "spriteSourceSize": { "x": 0, "y": 0, "w": 96, "h": 96 },
    "sourceSize": { "w": 96, "h": 96 },
    "duration": 71
   },
   {
    "filename": "frame-leo 16.aseprite",
    "frame": { "x": 0, "y": 192, "w": 96, "h": 96 },
    "rotated": false,
    "trimmed": false,
    "spriteSourceSize": { "x": 0, "y": 0, "w": 96, "h": 96 },
    "sourceSize": { "w": 96, "h": 96 },
    "duration": 71
   },
   {
    "filename": "frame-leo 17.aseprite",
    "frame": { "x": 96, "y": 192, "w": 96, "h": 96 },
    "rotated": false,
    "trimmed": false,
    "spriteSourceSize": { "x": 0, "y": 0, "w": 96, "h": 96 },
    "sourceSize": { "w": 96, "h": 96 },
    "duration": 71
   },
   {
    "filename": "frame-leo 18.aseprite",
    "frame": { "x": 192, "y": 192, "w": 96, "h": 96 },
    "rotated": false,
    "trimmed": false,
    "spriteSourceSize": { "x": 0, "y": 0, "w": 96, "h": 96 },
    "sourceSize": { "w": 96, "h": 96 },
    "duration": 71
   },
   {
    "filename": "frame-leo 19.aseprite",
    "frame": { "x": 288, "y": 192, "w": 96, "h": 96 },
    "rotated": false,
    "trimmed": false,
    "spriteSourceSize": { "x": 0, "y": 0, "w": 96, "h": 96 },
    "sourceSize": { "w": 96, "h": 96 },
    "duration": 71
   },
   {
    "filename": "frame-leo 20.aseprite",
    "frame": { "x": 384, "y": 192, "w": 96, "h": 96 },
    "rotated": false,
    "trimmed": false,
    "spriteSourceSize": { "x": 0, "y": 0, "w": 96, "h": 96 },
    "sourceSize": { "w": 96, "h": 96 },
    "duration": 71
   },
   {
    "filename": "frame-leo 21.aseprite",
    "frame": { "x": 0, "y": 288, "w": 96, "h": 96 },
    "rotated": false,
    "trimmed": false,
    "spriteSourceSize": { "x": 0, "y": 0, "w": 96, "h": 96 },
    "sourceSize": { "w": 96, "h": 96 },
    "duration": 71
   },
   {
    "filename": "frame-leo 22.aseprite",
    "frame": { "x": 96, "y": 288, "w": 96, "h": 96 },
    "rotated": false,
    "trimmed": false,
    "spriteSourceSize": { "x": 0, "y": 0, "w": 96, "h": 96 },
    "sourceSize": { "w": 96, "h": 96 },
    "duration": 71
   },
   {
    "filename": "frame-leo 23.aseprite",
    "frame": { "x": 192, "y": 288, "w": 96, "h": 96 },
    "rotated": false,
    "trimmed": false,
    "spriteSourceSize": { "x": 0, "y": 0, "w": 96, "h": 96 },
    "sourceSize": { "w": 96, "h": 96 },
    "duration": 71
   },
   {
    "filename": "frame-leo 24.aseprite",
    "frame": { "x": 288, "y": 288, "w": 96, "h": 96 },
    "rotated": false,
    "trimmed": false,
    "spriteSourceSize": { "x": 0, "y": 0, "w": 96, "h": 96 },
    "sourceSize": { "w": 96, "h": 96 },
    "duration": 71
   },
   {
    "filename": "frame-leo 25.aseprite",
    "frame": { "x": 288, "y": 288, "w": 96, "h": 96 },
    "rotated": false,
    "trimmed": false,
    "spriteSourceSize": { "x": 0, "y": 0, "w": 96, "h": 96 },
    "sourceSize": { "w": 96, "h": 96 },
    "duration": 71
   },
   {
    "filename": "frame-leo 26.aseprite",
    "frame": { "x": 288, "y": 288, "w": 96, "h": 96 },
    "rotated": false,
    "trimmed": false,
    "spriteSourceSize": { "x": 0, "y": 0, "w": 96, "h": 96 },
    "sourceSize": { "w": 96, "h": 96 },
    "duration": 71
   },
   {
    "filename": "frame-leo 27.aseprite",
    "frame": { "x": 288, "y": 288, "w": 96, "h": 96 },
    "rotated": false,
    "trimmed": false,
    "spriteSourceSize": { "x": 0, "y": 0, "w": 96, "h": 96 },
    "sourceSize": { "w": 96, "h": 96 },
    "duration": 71
   },
   {
    "filename": "frame-leo 28.aseprite",
    "frame": { "x": 192, "y": 288, "w": 96, "h": 96 },
    "rotated": false,
    "trimmed": false,
    "spriteSourceSize": { "x": 0, "y": 0, "w": 96, "h": 96 },
    "sourceSize": { "w": 96, "h": 96 },
    "duration": 71
   },
   {
    "filename": "frame-leo 29.aseprite",
    "frame": { "x": 192, "y": 288, "w": 96, "h": 96 },
    "rotated": false,
    "trimmed": false,
    "spriteSourceSize": { "x": 0, "y": 0, "w": 96, "h": 96 },
    "sourceSize": { "w": 96, "h": 96 },
    "duration": 71
   },
   {
    "filename": "frame-leo 30.aseprite",
    "frame": { "x": 192, "y": 288, "w": 96, "h": 96 },
    "rotated": false,
    "trimmed": false,
    "spriteSourceSize": { "x": 0, "y": 0, "w": 96, "h": 96 },
    "sourceSize": { "w": 96, "h": 96 },
    "duration": 71
   },
   {
    "filename": "frame-leo 31.aseprite",
    "frame": { "x": 192, "y": 288, "w": 96, "h": 96 },
    "rotated": false,
    "trimmed": false,
    "spriteSourceSize": { "x": 0, "y": 0, "w": 96, "h": 96 },
    "sourceSize": { "w": 96, "h": 96 },
    "duration": 71
   },
   {
    "filename": "frame-leo 32.aseprite",
    "frame": { "x": 288, "y": 288, "w": 96, "h": 96 },
    "rotated": false,
    "trimmed": false,
    "spriteSourceSize": { "x": 0, "y": 0, "w": 96, "h": 96 },
    "sourceSize": { "w": 96, "h": 96 },
    "duration": 71
   },
   {
    "filename": "frame-leo 33.aseprite",
    "frame": { "x": 288, "y": 288, "w": 96, "h": 96 },
    "rotated": false,
    "trimmed": false,
    "spriteSourceSize": { "x": 0, "y": 0, "w": 96, "h": 96 },
    "sourceSize": { "w": 96, "h": 96 },
    "duration": 71
   },
   {
    "filename": "frame-leo 34.aseprite",
    "frame": { "x": 288, "y": 288, "w": 96, "h": 96 },
    "rotated": false,
    "trimmed": false,
    "spriteSourceSize": { "x": 0, "y": 0, "w": 96, "h": 96 },
    "sourceSize": { "w": 96, "h": 96 },
    "duration": 71
   },
   {
    "filename": "frame-leo 35.aseprite",
    "frame": { "x": 288, "y": 288, "w": 96, "h": 96 },
    "rotated": false,
    "trimmed": false,
    "spriteSourceSize": { "x": 0, "y": 0, "w": 96, "h": 96 },
    "sourceSize": { "w": 96, "h": 96 },
    "duration": 71
   },
   {
    "filename": "frame-leo 36.aseprite",
    "frame": { "x": 192, "y": 288, "w": 96, "h": 96 },
    "rotated": false,
    "trimmed": false,
    "spriteSourceSize": { "x": 0, "y": 0, "w": 96, "h": 96 },
    "sourceSize": { "w": 96, "h": 96 },
    "duration": 71
   },
   {
    "filename": "frame-leo 37.aseprite",
    "frame": { "x": 192, "y": 288, "w": 96, "h": 96 },
    "rotated": false,
    "trimmed": false,
    "spriteSourceSize": { "x": 0, "y": 0, "w": 96, "h": 96 },
    "sourceSize": { "w": 96, "h": 96 },
    "duration": 71
   },
   {
    "filename": "frame-leo 38.aseprite",
    "frame": { "x": 192, "y": 288, "w": 96, "h": 96 },
    "rotated": false,
    "trimmed": false,
    "spriteSourceSize": { "x": 0, "y": 0, "w": 96, "h": 96 },
    "sourceSize": { "w": 96, "h": 96 },
    "duration": 71
   },
   {
    "filename": "frame-leo 39.aseprite",
    "frame": { "x": 192, "y": 288, "w": 96, "h": 96 },
    "rotated": false,
    "trimmed": false,
    "spriteSourceSize": { "x": 0, "y": 0, "w": 96, "h": 96 },
    "sourceSize": { "w": 96, "h": 96 },
    "duration": 71
   },
   {
    "filename": "frame-leo 40.aseprite",
    "frame": { "x": 288, "y": 288, "w": 96, "h": 96 },
    "rotated": false,
    "trimmed": false,
    "spriteSourceSize": { "x": 0, "y": 0, "w": 96, "h": 96 },
    "sourceSize": { "w": 96, "h": 96 },
    "duration": 71
   },
   {
    "filename": "frame-leo 41.aseprite",
    "frame": { "x": 288, "y": 288, "w": 96, "h": 96 },
    "rotated": false,
    "trimmed": false,
    "spriteSourceSize": { "x": 0, "y": 0, "w": 96, "h": 96 },
    "sourceSize": { "w": 96, "h": 96 },
    "duration": 71
   },
   {
    "filename": "frame-leo 42.aseprite",
    "frame": { "x": 288, "y": 288, "w": 96, "h": 96 },
    "rotated": false,
    "trimmed": false,
    "spriteSourceSize": { "x": 0, "y": 0, "w": 96, "h": 96 },
    "sourceSize": { "w": 96, "h": 96 },
    "duration": 71
   },
   {
    "filename": "frame-leo 43.aseprite",
    "frame": { "x": 288, "y": 288, "w": 96, "h": 96 },
    "rotated": false,
    "trimmed": false,
    "spriteSourceSize": { "x": 0, "y": 0, "w": 96, "h": 96 },
    "sourceSize": { "w": 96, "h": 96 },
    "duration": 71
   },


   {
    "filename": "frame-leo 36.aseprite",
    "frame": { "x": 192, "y": 288, "w": 96, "h": 96 },
    "rotated": false,
    "trimmed": false,
    "spriteSourceSize": { "x": 0, "y": 0, "w": 96, "h": 96 },
    "sourceSize": { "w": 96, "h": 96 },
    "duration": 71
   },
   {
    "filename": "frame-leo 37.aseprite",
    "frame": { "x": 192, "y": 288, "w": 96, "h": 96 },
    "rotated": false,
    "trimmed": false,
    "spriteSourceSize": { "x": 0, "y": 0, "w": 96, "h": 96 },
    "sourceSize": { "w": 96, "h": 96 },
    "duration": 71
   },
   {
    "filename": "frame-leo 38.aseprite",
    "frame": { "x": 192, "y": 288, "w": 96, "h": 96 },
    "rotated": false,
    "trimmed": false,
    "spriteSourceSize": { "x": 0, "y": 0, "w": 96, "h": 96 },
    "sourceSize": { "w": 96, "h": 96 },
    "duration": 71
   },
   {
    "filename": "frame-leo 39.aseprite",
    "frame": { "x": 192, "y": 288, "w": 96, "h": 96 },
    "rotated": false,
    "trimmed": false,
    "spriteSourceSize": { "x": 0, "y": 0, "w": 96, "h": 96 },
    "sourceSize": { "w": 96, "h": 96 },
    "duration": 71
   },
   {
    "filename": "frame-leo 40.aseprite",
    "frame": { "x": 288, "y": 288, "w": 96, "h": 96 },
    "rotated": false,
    "trimmed": false,
    "spriteSourceSize": { "x": 0, "y": 0, "w": 96, "h": 96 },
    "sourceSize": { "w": 96, "h": 96 },
    "duration": 71
   },
   {
    "filename": "frame-leo 41.aseprite",
    "frame": { "x": 288, "y": 288, "w": 96, "h": 96 },
    "rotated": false,
    "trimmed": false,
    "spriteSourceSize": { "x": 0, "y": 0, "w": 96, "h": 96 },
    "sourceSize": { "w": 96, "h": 96 },
    "duration": 71
   },
   {
    "filename": "frame-leo 42.aseprite",
    "frame": { "x": 288, "y": 288, "w": 96, "h": 96 },
    "rotated": false,
    "trimmed": false,
    "spriteSourceSize": { "x": 0, "y": 0, "w": 96, "h": 96 },
    "sourceSize": { "w": 96, "h": 96 },
    "duration": 71
   },
   {
    "filename": "frame-leo 43.aseprite",
    "frame": { "x": 288, "y": 288, "w": 96, "h": 96 },
    "rotated": false,
    "trimmed": false,
    "spriteSourceSize": { "x": 0, "y": 0, "w": 96, "h": 96 },
    "sourceSize": { "w": 96, "h": 96 },
    "duration": 71
   },


   {
    "filename": "frame-leo 36.aseprite",
    "frame": { "x": 192, "y": 288, "w": 96, "h": 96 },
    "rotated": false,
    "trimmed": false,
    "spriteSourceSize": { "x": 0, "y": 0, "w": 96, "h": 96 },
    "sourceSize": { "w": 96, "h": 96 },
    "duration": 71
   },
   {
    "filename": "frame-leo 37.aseprite",
    "frame": { "x": 192, "y": 288, "w": 96, "h": 96 },
    "rotated": false,
    "trimmed": false,
    "spriteSourceSize": { "x": 0, "y": 0, "w": 96, "h": 96 },
    "sourceSize": { "w": 96, "h": 96 },
    "duration": 71
   },
   {
    "filename": "frame-leo 38.aseprite",
    "frame": { "x": 192, "y": 288, "w": 96, "h": 96 },
    "rotated": false,
    "trimmed": false,
    "spriteSourceSize": { "x": 0, "y": 0, "w": 96, "h": 96 },
    "sourceSize": { "w": 96, "h": 96 },
    "duration": 71
   },
   {
    "filename": "frame-leo 39.aseprite",
    "frame": { "x": 192, "y": 288, "w": 96, "h": 96 },
    "rotated": false,
    "trimmed": false,
    "spriteSourceSize": { "x": 0, "y": 0, "w": 96, "h": 96 },
    "sourceSize": { "w": 96, "h": 96 },
    "duration": 71
   },
   {
    "filename": "frame-leo 40.aseprite",
    "frame": { "x": 288, "y": 288, "w": 96, "h": 96 },
    "rotated": false,
    "trimmed": false,
    "spriteSourceSize": { "x": 0, "y": 0, "w": 96, "h": 96 },
    "sourceSize": { "w": 96, "h": 96 },
    "duration": 71
   },
   {
    "filename": "frame-leo 41.aseprite",
    "frame": { "x": 288, "y": 288, "w": 96, "h": 96 },
    "rotated": false,
    "trimmed": false,
    "spriteSourceSize": { "x": 0, "y": 0, "w": 96, "h": 96 },
    "sourceSize": { "w": 96, "h": 96 },
    "duration": 71
   },
   {
    "filename": "frame-leo 42.aseprite",
    "frame": { "x": 288, "y": 288, "w": 96, "h": 96 },
    "rotated": false,
    "trimmed": false,
    "spriteSourceSize": { "x": 0, "y": 0, "w": 96, "h": 96 },
    "sourceSize": { "w": 96, "h": 96 },
    "duration": 71
   },
   {
    "filename": "frame-leo 43.aseprite",
    "frame": { "x": 288, "y": 288, "w": 96, "h": 96 },
    "rotated": false,
    "trimmed": false,
    "spriteSourceSize": { "x": 0, "y": 0, "w": 96, "h": 96 },
    "sourceSize": { "w": 96, "h": 96 },
    "duration": 71
   },


   {
    "filename": "frame-leo 36.aseprite",
    "frame": { "x": 192, "y": 288, "w": 96, "h": 96 },
    "rotated": false,
    "trimmed": false,
    "spriteSourceSize": { "x": 0, "y": 0, "w": 96, "h": 96 },
    "sourceSize": { "w": 96, "h": 96 },
    "duration": 71
   },
   {
    "filename": "frame-leo 37.aseprite",
    "frame": { "x": 192, "y": 288, "w": 96, "h": 96 },
    "rotated": false,
    "trimmed": false,
    "spriteSourceSize": { "x": 0, "y": 0, "w": 96, "h": 96 },
    "sourceSize": { "w": 96, "h": 96 },
    "duration": 71
   },
   {
    "filename": "frame-leo 38.aseprite",
    "frame": { "x": 192, "y": 288, "w": 96, "h": 96 },
    "rotated": false,
    "trimmed": false,
    "spriteSourceSize": { "x": 0, "y": 0, "w": 96, "h": 96 },
    "sourceSize": { "w": 96, "h": 96 },
    "duration": 71
   },
   {
    "filename": "frame-leo 39.aseprite",
    "frame": { "x": 192, "y": 288, "w": 96, "h": 96 },
    "rotated": false,
    "trimmed": false,
    "spriteSourceSize": { "x": 0, "y": 0, "w": 96, "h": 96 },
    "sourceSize": { "w": 96, "h": 96 },
    "duration": 71
   },
   {
    "filename": "frame-leo 40.aseprite",
    "frame": { "x": 288, "y": 288, "w": 96, "h": 96 },
    "rotated": false,
    "trimmed": false,
    "spriteSourceSize": { "x": 0, "y": 0, "w": 96, "h": 96 },
    "sourceSize": { "w": 96, "h": 96 },
    "duration": 71
   },
   {
    "filename": "frame-leo 41.aseprite",
    "frame": { "x": 288, "y": 288, "w": 96, "h": 96 },
    "rotated": false,
    "trimmed": false,
    "spriteSourceSize": { "x": 0, "y": 0, "w": 96, "h": 96 },
    "sourceSize": { "w": 96, "h": 96 },
    "duration": 71
   },
   {
    "filename": "frame-leo 42.aseprite",
    "frame": { "x": 288, "y": 288, "w": 96, "h": 96 },
    "rotated": false,
    "trimmed": false,
    "spriteSourceSize": { "x": 0, "y": 0, "w": 96, "h": 96 },
    "sourceSize": { "w": 96, "h": 96 },
    "duration": 71
   },
   {
    "filename": "frame-leo 43.aseprite",
    "frame": { "x": 288, "y": 288, "w": 96, "h": 96 },
    "rotated": false,
    "trimmed": false,
    "spriteSourceSize": { "x": 0, "y": 0, "w": 96, "h": 96 },
    "sourceSize": { "w": 96, "h": 96 },
    "duration": 15000
   }
 ],
 "meta": {
  "app": "https://www.aseprite.org/",
  "version": "1.3-rc4-x64",
  "image": "manhole_flip_leo.png",
  "format": "RGBA8888",
  "size": { "w": 480, "h": 384 },
  "scale": "1",
  "frameTags": [
  ],
  "layers": [
   { "name": "Layer 1", "opacity": 255, "blendMode": "normal" },
   { "name": "Layer 2", "opacity": 255, "blendMode": "normal" },
   { "name": "Layer 3", "opacity": 255, "blendMode": "normal" }
  ],
  "slices": [
  ]
 }
}
